[{"schema_version":"2.0.0","country_id":"panama","slug":"panama","status":"reviewed","page_kind":"country","last_reviewed":"2026-06-29","public_display_ceiling":"C","source_test_status":"partial","hero":{"summary_en":"Official programme pages confirm meeting dates for Hipódromo Presidente Remón.","summary_ja":"公式番組ページでHipódromo Presidente Remónの開催日を確認済み。"},"overview":{"paragraphs_en":["The reviewed scope is limited to Hipódromo Presidente Remón.","Stable event permalinks support a bounded meeting-date prototype."],"paragraphs_ja":["確認済み範囲はHipódromo Presidente Remónに限定する。","安定したイベント固定URLにより限定的な開催日プロトタイプが可能。"]},"racing_types":[{"id":"thoroughbred-flat","name_en":"Flat racing","name_ja":"平地競走","summary_en":"Reviewed for Hipódromo Presidente Remón.","summary_ja":"Hipódromo Presidente Remónで確認済み。"}],"seasonality":{"pattern":"official-source-required","summary_en":"Check the current official programme category.","summary_ja":"現行の公式番組カテゴリを確認する。"},"schedule":{"timezone":"America/Panama","utc_offset_label":"Verify current local offset","day_patterns":["official-source-required"],"time_patterns":["meeting-date-only"],"summary_en":"Meeting dates are confirmed; page operating hours are not race times.","summary_ja":"開催日は確認済みだが、ページ上の営業時間はレース時刻ではない。"},"surfaces":{"ids":[],"summary_en":"Not normalized.","summary_ja":"共通化しない。"},"systems":[{"id":"panama-presidente-remon-system","name_en":"Hipódromo Presidente Remón programme","name_ja":"Hipódromo Presidente Remón番組","summary_en":"Reviewed single-racecourse event-page context.","summary_ja":"確認済み単一競馬場イベントページ文脈。","organiser_source_ids":["panama-presidente-remon-programme"],"distributor_source_ids":[]}],"principal_racecourse_ids":[],"calendar_guidance_en":"Use official event permalinks for meeting dates only and never treat operating hours as post times.","calendar_guidance_ja":"公式イベント固定URLから開催日のみを使用し、営業時間を発走時刻として扱わない。","coverage_note_en":"Only Hipódromo Presidente Remón is reviewed; countrywide coverage is not established.","coverage_note_ja":"Hipódromo Presidente Remónのみ確認済みで、全国網羅性は未確立。","revalidation":{"triggers_en":["Programme category changes","Event permalink structure changes","Operator identity changes"],"triggers_ja":["番組カテゴリ変更時","イベント固定URL構造変更時","運営主体変更時"]},"related_glossary_ids":["racecourse","meeting","fixture","post-time"]}]